Workbook

Sheet README
A1: מודל DCF — דוגמה
A2: תאים לעריכה: Assumptions!C2:C11 (כחול); אופק נקבע בבנייה עם --N (אפור)
A3: גרסה: 0.1
A4: תאריך בנייה: דטרמיניסטי — ראה rebuild_compare
A5: המודל מחשב בלבד — אינו ייעוץ השקעות.

Sheet Assumptions
A1: key | B1: label | C1: value | D1: unit | E1: source
A2: rev0 | B2: הכנסות שנת בסיס | C2: 10000000 | D2: ₪ | E2: המשתמש
A3: growth | B3: צמיחת הכנסות | C3: 0.08 | D3: % | E3: המשתמש
A4: margin | B4: מרווח EBIT | C4: 0.2 | D4: % | E4: המשתמש
A5: tax_corp | B5: מס חברות | C5: 0.23 | D5: % | E5: המשתמש
A6: dep_pct | B6: פחת % מהכנסות | C6: 0.04 | D6: % | E6: המשתמש
A7: capex_pct | B7: CapEx % מהכנסות | C7: 0.05 | D7: % | E7: המשתמש
A8: nwc_pct | B8: הון חוזר % מהכנסות | C8: 0.1 | D8: % | E8: המשתמש
A9: wacc | B9: WACC | C9: 0.1 | D9: % | E9: הנחה — לאישור
A10: g_terminal | B10: צמיחה טרמינלית | C10: 0.02 | D10: % | E10: הנחה — לאישור
A11: investment | B11: השקעה ראשונית | C11: 8000000 | D11: ₪ | E11: המשתמש
A12: horizon | B12: אופק (שנים) | C12: 5 | D12: שנים | E12: CLI --N

Sheet Calc
A1: key | B1: label | C1: 0 | D1: 1 | E1: 2 | F1: 3 | G1: 4 | H1: 5
A2: revenue | B2: הכנסות | C2: =Assumptions!$C$2 -> 10000000 | D2: =C2*(1+Assumptions!$C$3) -> 10800000 | E2: =D2*(1+Assumptions!$C$3) -> 11664000 | F2: =E2*(1+Assumptions!$C$3) -> 12597120 | G2: =F2*(1+Assumptions!$C$3) -> 13604890 | H2: =G2*(1+Assumptions!$C$3) -> 14693281
A3: ebit | B3: EBIT | C3: =C2*Assumptions!$C$4 -> 2000000 | D3: =D2*Assumptions!$C$4 -> 2160000 | E3: =E2*Assumptions!$C$4 -> 2332800 | F3: =F2*Assumptions!$C$4 -> 2519424 | G3: =G2*Assumptions!$C$4 -> 2720977.9 | H3: =H2*Assumptions!$C$4 -> 2938656.2
A4: tax | B4: מס | C4: =C3*Assumptions!$C$5 -> 460000 | D4: =D3*Assumptions!$C$5 -> 496800 | E4: =E3*Assumptions!$C$5 -> 536544 | F4: =F3*Assumptions!$C$5 -> 579467.52 | G4: =G3*Assumptions!$C$5 -> 625824.92 | H4: =H3*Assumptions!$C$5 -> 675890.92
A5: nopat | B5: NOPAT | C5: =C3-C4 -> 1540000 | D5: =D3-D4 -> 1663200 | E5: =E3-E4 -> 1796256 | F5: =F3-F4 -> 1939956.5 | G5: =G3-G4 -> 2095153 | H5: =H3-H4 -> 2262765.2
A6: dep | B6: פחת | C6: =C2*Assumptions!$C$6 -> 400000 | D6: =D2*Assumptions!$C$6 -> 432000 | E6: =E2*Assumptions!$C$6 -> 466560 | F6: =F2*Assumptions!$C$6 -> 503884.8 | G6: =G2*Assumptions!$C$6 -> 544195.58 | H6: =H2*Assumptions!$C$6 -> 587731.23
A7: capex | B7: CapEx | C7: =C2*Assumptions!$C$7 -> 500000 | D7: =D2*Assumptions!$C$7 -> 540000 | E7: =E2*Assumptions!$C$7 -> 583200 | F7: =F2*Assumptions!$C$7 -> 629856 | G7: =G2*Assumptions!$C$7 -> 680244.48 | H7: =H2*Assumptions!$C$7 -> 734664.04
A8: nwc | B8: הון חוזר | C8: =C2*Assumptions!$C$8 -> 1000000 | D8: =D2*Assumptions!$C$8 -> 1080000 | E8: =E2*Assumptions!$C$8 -> 1166400 | F8: =F2*Assumptions!$C$8 -> 1259712 | G8: =G2*Assumptions!$C$8 -> 1360489 | H8: =H2*Assumptions!$C$8 -> 1469328.1
A9: dnwc | B9: שינוי בהון חוזר | C9: =0*C8 -> 0 | D9: =D8-C8 -> 80000 | E9: =E8-D8 -> 86400 | F9: =F8-E8 -> 93312 | G9: =G8-F8 -> 100776.96 | H9: =H8-G8 -> 108839.12
A10: fcf | B10: FCF | C10: =-Assumptions!$C$11 -> -8000000 | D10: =D5+D6-D7-D9 -> 1475200 | E10: =E5+E6-E7-E9 -> 1593216 | F10: =F5+F6-F7-F9 -> 1720673.3 | G10: =G5+G6-G7-G9 -> 1858327.1 | H10: =H5+H6-H7-H9 -> 2006993.3
A11: df | B11: מקדם היוון | C11: =1/(1+Assumptions!$C$9)^C$1 -> 1 | D11: =1/(1+Assumptions!$C$9)^D$1 -> 0.90909091 | E11: =1/(1+Assumptions!$C$9)^E$1 -> 0.82644628 | F11: =1/(1+Assumptions!$C$9)^F$1 -> 0.7513148 | G11: =1/(1+Assumptions!$C$9)^G$1 -> 0.68301346 | H11: =1/(1+Assumptions!$C$9)^H$1 -> 0.62092132
A12: pv | B12: ערך נוכחי | C12: =C10*C11 -> -8000000 | D12: =D10*D11 -> 1341090.9 | E12: =E10*E11 -> 1316707.4 | F12: =F10*F11 -> 1292767.3 | G12: =G10*G11 -> 1269262.4 | H12: =H10*H11 -> 1246184.9

Sheet Output
A1: סה"כ ערך נוכחי של התזרימים | B1: =SUM(Calc!C12:H12) -> -1533987
A2: ערך טרמינלי (מהוון) | B2: =IF(Assumptions!$C$9>Assumptions!$C$10,Calc!H10*(1+Assumptions!$C$10)/(Assumptions!$C$9-Assumptions!$C$10)*Calc!H11,NA()) -> 15888858
A3: NPV (כולל השקעה) | B3: =B1+B2 -> 14354871
A4: IRR (ללא ערך טרמינלי) | B4: =IRR(Calc!C10:H10) -> 0.025450707
A6: ניתוח רגישות: NPV — WACC (שורות) × צמיחה טרמינלית (עמודות)
B7: 0 | C7: 0.01 | D7: 0.02 | E7: 0.03
A8: 0.08 | B8: =IF($A8>B$7,SUMPRODUCT(Calc!$C$10:$H$10/(1+$A8)^Calc!$C$1:$H$1)+Calc!$H$10*(1+B$7)/($A8-B$7)/(1+$A8)^Assumptions!$C$12,NA()) -> 15903704 | C8: =IF($A8>C$7,SUMPRODUCT(Calc!$C$10:$H$10/(1+$A8)^Calc!$C$1:$H$1)+Calc!$H$10*(1+C$7)/($A8-C$7)/(1+$A8)^Assumptions!$C$12,NA()) -> 18537989 | D8: =IF($A8>D$7,SUMPRODUCT(Calc!$C$10:$H$10/(1+$A8)^Calc!$C$1:$H$1)+Calc!$H$10*(1+D$7)/($A8-D$7)/(1+$A8)^Assumptions!$C$12,NA()) -> 22050370 | E8: =IF($A8>E$7,SUMPRODUCT(Calc!$C$10:$H$10/(1+$A8)^Calc!$C$1:$H$1)+Calc!$H$10*(1+E$7)/($A8-E$7)/(1+$A8)^Assumptions!$C$12,NA()) -> 26967704
A9: 0.09 | B9: =IF($A9>B$7,SUMPRODUCT(Calc!$C$10:$H$10/(1+$A9)^Calc!$C$1:$H$1)+Calc!$H$10*(1+B$7)/($A9-B$7)/(1+$A9)^Assumptions!$C$12,NA()) -> 13137363 | C9: =IF($A9>C$7,SUMPRODUCT(Calc!$C$10:$H$10/(1+$A9)^Calc!$C$1:$H$1)+Calc!$H$10*(1+C$7)/($A9-C$7)/(1+$A9)^Assumptions!$C$12,NA()) -> 15112092 | D9: =IF($A9>D$7,SUMPRODUCT(Calc!$C$10:$H$10/(1+$A9)^Calc!$C$1:$H$1)+Calc!$H$10*(1+D$7)/($A9-D$7)/(1+$A9)^Assumptions!$C$12,NA()) -> 17651029 | E9: =IF($A9>E$7,SUMPRODUCT(Calc!$C$10:$H$10/(1+$A9)^Calc!$C$1:$H$1)+Calc!$H$10*(1+E$7)/($A9-E$7)/(1+$A9)^Assumptions!$C$12,NA()) -> 21036278
A10: 0.1 | B10: =IF($A10>B$7,SUMPRODUCT(Calc!$C$10:$H$10/(1+$A10)^Calc!$C$1:$H$1)+Calc!$H$10*(1+B$7)/($A10-B$7)/(1+$A10)^Assumptions!$C$12,NA()) -> 10927862 | C10: =IF($A10>C$7,SUMPRODUCT(Calc!$C$10:$H$10/(1+$A10)^Calc!$C$1:$H$1)+Calc!$H$10*(1+C$7)/($A10-C$7)/(1+$A10)^Assumptions!$C$12,NA()) -> 12450977 | D10: =IF($A10>D$7,SUMPRODUCT(Calc!$C$10:$H$10/(1+$A10)^Calc!$C$1:$H$1)+Calc!$H$10*(1+D$7)/($A10-D$7)/(1+$A10)^Assumptions!$C$12,NA()) -> 14354871 | E10: =IF($A10>E$7,SUMPRODUCT(Calc!$C$10:$H$10/(1+$A10)^Calc!$C$1:$H$1)+Calc!$H$10*(1+E$7)/($A10-E$7)/(1+$A10)^Assumptions!$C$12,NA()) -> 16802734
A11: 0.11 | B11: =IF($A11>B$7,SUMPRODUCT(Calc!$C$10:$H$10/(1+$A11)^Calc!$C$1:$H$1)+Calc!$H$10*(1+B$7)/($A11-B$7)/(1+$A11)^Assumptions!$C$12,NA()) -> 9123184 | C11: =IF($A11>C$7,SUMPRODUCT(Calc!$C$10:$H$10/(1+$A11)^Calc!$C$1:$H$1)+Calc!$H$10*(1+C$7)/($A11-C$7)/(1+$A11)^Assumptions!$C$12,NA()) -> 10325065 | D11: =IF($A11>D$7,SUMPRODUCT(Calc!$C$10:$H$10/(1+$A11)^Calc!$C$1:$H$1)+Calc!$H$10*(1+D$7)/($A11-D$7)/(1+$A11)^Assumptions!$C$12,NA()) -> 11794030 | E11: =IF($A11>E$7,SUMPRODUCT(Calc!$C$10:$H$10/(1+$A11)^Calc!$C$1:$H$1)+Calc!$H$10*(1+E$7)/($A11-E$7)/(1+$A11)^Assumptions!$C$12,NA()) -> 13630236
A12: 0.12 | B12: =IF($A12>B$7,SUMPRODUCT(Calc!$C$10:$H$10/(1+$A12)^Calc!$C$1:$H$1)+Calc!$H$10*(1+B$7)/($A12-B$7)/(1+$A12)^Assumptions!$C$12,NA()) -> 7621991.1 | C12: =IF($A12>C$7,SUMPRODUCT(Calc!$C$10:$H$10/(1+$A12)^Calc!$C$1:$H$1)+Calc!$H$10*(1+C$7)/($A12-C$7)/(1+$A12)^Assumptions!$C$12,NA()) -> 8588264.2 | D12: =IF($A12>D$7,SUMPRODUCT(Calc!$C$10:$H$10/(1+$A12)^Calc!$C$1:$H$1)+Calc!$H$10*(1+D$7)/($A12-D$7)/(1+$A12)^Assumptions!$C$12,NA()) -> 9747792 | E12: =IF($A12>E$7,SUMPRODUCT(Calc!$C$10:$H$10/(1+$A12)^Calc!$C$1:$H$1)+Calc!$H$10*(1+E$7)/($A12-E$7)/(1+$A12)^Assumptions!$C$12,NA()) -> 11164993
